setup.cfg
setup.py
figit/__init__.py
figit/figit.py
figit.egg-info/PKG-INFO
figit.egg-info/SOURCES.txt
figit.egg-info/dependency_links.txt
figit.egg-info/entry_points.txt
figit.egg-info/requires.txt
figit.egg-info/top_level.txt