Metadata-Version: 1.1
Name: figit
Version: 1.1.1
Summary: Upload images to your github enterprise server.
Home-page: https://github.com/smlstvnh/figit
Author: samstav
Author-email: smlstvnh@gmail.com
License: Apache 2
Keywords: figit
Platform: UNKNOWN
Classifier: Programming Language :: Python
